[{"civid":"Greek","level":5,"rewardids":{"id":["C01_L05_A","C01_L05_B"]}},{"civid":"Greek","level":10,"rewardids":{"id":["C01_L10_A","C01_L10_B"]}},{"civid":"Greek","level":20,"rewardids":{"id":["C01_L20_A","C01_L20_B"]}},{"civid":"Greek","level":30,"rewardids":{"id":["C01_L30_A","C01_L30_B"]}},{"civid":"Greek","level":40,"rewardids":{"id":["C01_L40_A","C01_L40_B"]}},{"civid":"Egyptian","level":5,"rewardids":{"id":["C02_L05_A","C02_L05_B"]}},{"civid":"Egyptian","level":10,"rewardids":{"id":["C02_L10_A","C02_L10_B"]}},{"civid":"Egyptian","level":20,"rewardids":{"id":["C02_L20_A","C02_L20_B"]}},{"civid":"Egyptian","level":30,"rewardids":{"id":["C02_L30_A","C02_L30_B"]}},{"civid":"Egyptian","level":40,"rewardids":{"id":["C02_L40_A","C02_L40_B"]}},{"civid":"Celtic","level":5,"rewardids":{"id":["C03_L05_A","C03_L05_B"]}},{"civid":"Celtic","level":10,"rewardids":{"id":["C03_L10_A","C03_L10_B"]}},{"civid":"Celtic","level":20,"rewardids":{"id":["C03_L20_A","C03_L20_B"]}},{"civid":"Celtic","level":30,"rewardids":{"id":["C03_L30_A","C03_L30_B"]}},{"civid":"Celtic","level":40,"rewardids":{"id":["C03_L40_A","C03_L40_B"]}},{"civid":"Persian","level":5,"rewardids":{"id":["C04_L05_A","C04_L05_B"]}},{"civid":"Persian","level":10,"rewardids":{"id":["C04_L10_A","C04_L10_B"]}},{"civid":"Persian","level":20,"rewardids":{"id":["C04_L20_A","C04_L20_B"]}},{"civid":"Persian","level":30,"rewardids":{"id":["C04_L30_A","C04_L30_B"]}},{"civid":"Persian","level":40,"rewardids":{"id":["C04_L40_A","C04_L40_B"]}},{"civid":"Roman","level":5,"rewardids":{"id":["C05_L05_A","C05_L05_B"]}},{"civid":"Roman","level":10,"rewardids":{"id":["C05_L10_A","C05_L10_B"]}},{"civid":"Roman","level":20,"rewardids":{"id":["C05_L20_A","C05_L20_B"]}},{"civid":"Roman","level":30,"rewardids":{"id":["C05_L30_A","C05_L30_B"]}},{"civid":"Roman","level":40,"rewardids":{"id":["C05_L40_A","C05_L40_B"]}},{"civid":"Babylonian","level":5,"rewardids":{"id":["C06_L05_A","C06_L05_B"]}},{"civid":"Babylonian","level":10,"rewardids":{"id":["C06_L10_A","C06_L10_B"]}},{"civid":"Babylonian","level":20,"rewardids":{"id":["C06_L20_A","C06_L20_B"]}},{"civid":"Babylonian","level":30,"rewardids":{"id":["C06_L30_A","C06_L30_B"]}},{"civid":"Babylonian","level":40,"rewardids":{"id":["C06_L40_A","C06_L40_B"]}},{"civid":"Norse","level":5,"rewardids":{"id":["C07_L05_A","C07_L05_B"]}},{"civid":"Norse","level":10,"rewardids":{"id":["C07_L10_A","C07_L10_B"]}},{"civid":"Norse","level":20,"rewardids":{"id":["C07_L20_A","C07_L20_B"]}},{"civid":"Norse","level":30,"rewardids":{"id":["C07_L30_A","C07_L30_B"]}},{"civid":"Norse","level":40,"rewardids":{"id":["C07_L40_A","C07_L40_B"]}},{"civid":"Indian","level":5,"rewardids":{"id":["C08_L05_A","C08_L05_B"]}},{"civid":"Indian","level":10,"rewardids":{"id":["C08_L10_A","C08_L10_B"]}},{"civid":"Indian","level":20,"rewardids":{"id":["C08_L20_A","C08_L20_B"]}},{"civid":"Indian","level":30,"rewardids":{"id":["C08_L30_A","C08_L30_B"]}},{"civid":"Indian","level":40,"rewardids":{"id":["C08_L40_A","C08_L40_B"]}}]